dnv/sesam/__init__.py
dnv/sesam/commands/__init__.py
dnv/sesam/commands/executable_command_base.py
dnv/sesam/commands/generic_sesam_command.py
dnv/sesam/commands/genie_runtime_command.py
dnv/sesam/commands/infidep_calibration_command.py
dnv/sesam/commands/infidep_work_unit.py
dnv/sesam/commands/sesam_core_command.py
dnv/sesam/commands/sesam_worker_command.py
dnv/sesam/commands/sestra_command.py
dnv/sesam/commands/sima_command.py
dnv/sesam/commands/wadam_command.py
dnv/sesam/commands/wajac_command.py
dnv/sesam/commands/wasim_command.py
dnv/sesam/commands/executors/__init__.py
dnv/sesam/commands/executors/__init__.pyi
dnv/sesam/commands/executors/_app_installer.py
dnv/sesam/commands/executors/_type_converter.py
dnv/sesam/commands/executors/command_executor.py
dnv/sesam/commands/executors/sima_cmd_executor.py
dnv/sesam/commands/executors/.dlls/Azure.Core.dll
dnv/sesam/commands/executors/.dlls/Azure.Data.Tables.dll
dnv/sesam/commands/executors/.dlls/Azure.Identity.dll
dnv/sesam/commands/executors/.dlls/Azure.Storage.Blobs.dll
dnv/sesam/commands/executors/.dlls/Azure.Storage.Common.dll
dnv/sesam/commands/executors/.dlls/Azure.Storage.Queues.dll
dnv/sesam/commands/executors/.dlls/DNV.One.Compute.ApplicationManagement.dll
dnv/sesam/commands/executors/.dlls/DNV.One.Compute.Core.dll
dnv/sesam/commands/executors/.dlls/DNV.One.Compute.StorageLibrary.Azure.dll
dnv/sesam/commands/executors/.dlls/DNV.One.Compute.StorageLibrary.dll
dnv/sesam/commands/executors/.dlls/DNV.One.Workflow.Deployment.dll
dnv/sesam/commands/executors/.dlls/Microsoft.Azure.KeyVault.Core.dll
dnv/sesam/commands/executors/.dlls/Microsoft.Azure.Storage.Blob.dll
dnv/sesam/commands/executors/.dlls/Microsoft.Azure.Storage.Common.dll
dnv/sesam/commands/executors/.dlls/Microsoft.Azure.Storage.DataMovement.dll
dnv/sesam/commands/executors/.dlls/Microsoft.Azure.Storage.File.dll
dnv/sesam/commands/executors/.dlls/Microsoft.Bcl.AsyncInterfaces.dll
dnv/sesam/commands/executors/.dlls/Microsoft.Data.Edm.dll
dnv_sesam_commands-5.23.1.0.dist-info/licenses/LICENSE
dnv_sesam_commands-5.23.1.0.dist-info/METADATA
dnv_sesam_commands-5.23.1.0.dist-info/WHEEL
dnv_sesam_commands-5.23.1.0.dist-info/top_level.txt
dnv_sesam_commands-5.23.1.0.dist-info/RECORD
