Metadata-Version: 2.4
Name: dnv-sesam-commands
Version: 5.23.1.0
Summary: A Python library for developing and executing Sesam workflows on local or cloud platforms, and for executing commands outside of workflow contexts.
Author-email: DNV AS <software.support@dnv.com>
License: MIT License
Project-URL: Homepage, https://myworkspace.dnv.com/knowledge-centre/sesam-workflows/usermanual/?document=sesam-workflows-getstarted
Keywords: onecompute,oneworkflow,workflow,sesam
Classifier: License :: OSI Approved :: MIT License
Classifier: Programming Language :: Python
Classifier: Programming Language :: Python :: 3.10
Classifier: Programming Language :: Python :: 3.11
Classifier: Programming Language :: Python :: 3.12
Requires-Python: >=3.10
License-File: LICENSE
Requires-Dist: dnv-oneworkflow<2,>=1.0.0
Requires-Dist: dnv-net-runtime
Requires-Dist: multipledispatch
Dynamic: license-file
